skyfield_data/__init__.py
skyfield_data/expiration_data.py
skyfield_data/expirations.py
skyfield_data/data/de421.bsp
skyfield_data/data/finals2000A.all
skyfield_data-7.0.0.dist-info/licenses/COPYING
skyfield_data-7.0.0.dist-info/METADATA
skyfield_data-7.0.0.dist-info/WHEEL
skyfield_data-7.0.0.dist-info/top_level.txt
skyfield_data-7.0.0.dist-info/RECORD
