Metadata-Version: 2.4
Name: skyfield-data
Version: 7.0.0
Summary: Data package for Skyfield
Home-page: https://github.com/brunobord/skyfield-data
Author: Bruno Bord
Author-email: bruno@jehaisleprintemps.net
License: MIT
Keywords: astronomy science
Platform: any
Classifier: Development Status :: 5 - Production/Stable
Classifier: Intended Audience :: Developers
Classifier: License :: OSI Approved :: MIT License
Classifier: Operating System :: OS Independent
Classifier: Programming Language :: Python
Classifier: Programming Language :: Python :: 2.6
Classifier: Programming Language :: Python :: 2.7
Classifier: Programming Language :: Python :: 3.8
Classifier: Programming Language :: Python :: 3.9
Classifier: Programming Language :: Python :: 3.10
Classifier: Programming Language :: Python :: 3.11
Classifier: Programming Language :: Python :: 3.12
Classifier: Programming Language :: Python :: 3.13
Requires-Python: !=3.0.*,!=3.1.*,!=3.2.*,!=3.3.*,!=3.4.*,!=3.5.*,!=3.6.*,!=3.7,<4,>=2.6
License-File: COPYING
Provides-Extra: dev
Requires-Dist: jplephem; extra == "dev"
Requires-Dist: numpy; extra == "dev"
Requires-Dist: tox; extra == "dev"
Requires-Dist: colorama; extra == "dev"
Requires-Dist: termcolor; extra == "dev"
Provides-Extra: tests
Requires-Dist: pytest; extra == "tests"
Requires-Dist: skyfield; extra == "tests"
Requires-Dist: mock; extra == "tests"
Dynamic: license-file
